images_compare/__init__.py
images_compare/verify.py
images_compare-0.6.0.dist-info/LICENSE.txt
images_compare-0.6.0.dist-info/METADATA
images_compare-0.6.0.dist-info/WHEEL
images_compare-0.6.0.dist-info/top_level.txt
images_compare-0.6.0.dist-info/RECORD
