Metadata-Version: 2.1
Name: images-compare
Version: 0.6.0
Summary: This Python package allows for image comparison between two provided images using a specified threshold
Home-page: https://github.com/denzilrdz/images-compare
Author: Denzil Rodrigues
Author-email: denzil.rdz@gmail.com
License: MIT
Classifier: License :: OSI Approved :: MIT License
Classifier: Programming Language :: Python :: 3.11
Classifier: Operating System :: OS Independent
Requires-Python: >=3.11
License-File: LICENSE.txt
Requires-Dist: numpy (>=1.25.0)
Requires-Dist: opencv-python (>=4.7.0.72)
